README.rst
setup.py
datatables/__init__.py
datatables.egg-info/PKG-INFO
datatables.egg-info/SOURCES.txt
datatables.egg-info/dependency_links.txt
datatables.egg-info/not-zip-safe
datatables.egg-info/top_level.txt